src/__init__.py
src/myloop.py
myloop-0.0.1.dist-info/METADATA
myloop-0.0.1.dist-info/WHEEL
myloop-0.0.1.dist-info/licenses/LICENSE
myloop-0.0.1.dist-info/RECORD
