Metadata-Version: 2.1
Name: myloop
Version: 0.0.1
Summary: My implantation for how the loop Shell command should be
Project-URL: Homepage, https://github.com/mashayev/myloop
Project-URL: Bug Tracker, https://github.com/mashayev/myloop/issues
Author-email: Eddie Mashayev <eddiem21@gmail.com>
License: MIT License
License-File: LICENSE
Classifier: License :: OSI Approved :: MIT License
Classifier: Operating System :: OS Independent
Classifier: Programming Language :: Python :: 3.10
Requires-Python: >=3.10
